keycripty/__error__.py
keycripty/__init__.py
keycripty/caracters.py
keycripty/hash_dados.py
keycripty/hash_file.py
keycripty/keycripty.py
keycripty-0.4.1.dist-info/LICENSE
keycripty-0.4.1.dist-info/METADATA
keycripty-0.4.1.dist-info/WHEEL
keycripty-0.4.1.dist-info/top_level.txt
keycripty-0.4.1.dist-info/RECORD
