Metadata-Version: 2.1
Name: keycripty
Version: 0.4.1
Summary: keycripty é um Framework para criptografia.
Home-page: https://github.com/cesarneves-security/keycrypt
Author: César Neves
Author-email: cesarioneves104@gmail.com
Classifier: Programming Language :: Python :: 3
Classifier: License :: OSI Approved :: MIT License
Classifier: Operating System :: OS Independent
Requires-Python: >=3.6
License-File: LICENSE
